brewinglib/generic/__init__.py
brewinglib/generic/py.typed
brewinglib_generic-0.0.6.dist-info/METADATA
brewinglib_generic-0.0.6.dist-info/WHEEL
brewinglib_generic-0.0.6.dist-info/RECORD
