Metadata-Version: 2.4
Name: brewinglib-generic
Version: 0.0.6
Summary: Convert a class with generic type parameters to be generic at runtime.
Project-URL: Homepage, https://mikemcowie.github.io/brewing/
Project-URL: Documentation, https://mikemcowie.github.io/brewing/
Project-URL: Repository, https://github.com/mikemcowie/brewing
Project-URL: Issues, https://github.com/mikemcowie/brewing
Project-URL: Releases, https://github.com/mikemcowie/brewing/releases
Author-email: Mike Cowie <24739590+mikemcowie@users.noreply.github.com>
Requires-Python: >=3.13
